py_profiler/__init__.py
py_profiler/decorator.py
py_profiler/fastapi_profiler_controller.py
py_profiler/long_adder.py
py_profiler/measure_service.py
py_profiler/profiler_controller.py
py_profiler/utils.py
py_profiler/templates/profiler.html
py_profiler-0.3.1.dist-info/LICENSE
py_profiler-0.3.1.dist-info/METADATA
py_profiler-0.3.1.dist-info/WHEEL
py_profiler-0.3.1.dist-info/top_level.txt
py_profiler-0.3.1.dist-info/RECORD
