Metadata-Version: 2.1
Name: py_profiler
Version: 0.3.1
Summary: A library to measure your method, function execution time.
Home-page: https://github.com/andy1xx8/py-profiler
Author: Andy Le
Author-email: tauit.dnmd@gmail.com
Project-URL: Bug Tracker, https://github.com/andy1xx8/py-profiler/issues
Classifier: Programming Language :: Python :: 3
Classifier: License :: OSI Approved :: MIT License
Classifier: Operating System :: OS Independent
Requires-Python: >=3.8
License-File: LICENSE
Requires-Dist: jinja2
Requires-Dist: beautifultable
Requires-Dist: asyncio
